AUTHORS.rst
CHANGELOG.rst
LICENSE
MANIFEST.in
README.rst
setup.py
panya_playlist.egg-info/PKG-INFO
panya_playlist.egg-info/SOURCES.txt
panya_playlist.egg-info/dependency_links.txt
panya_playlist.egg-info/not-zip-safe
panya_playlist.egg-info/requires.txt
panya_playlist.egg-info/top_level.txt
playlist/__init__.py
playlist/admin.py
playlist/managers.py
playlist/models.py
playlist/tests.py
playlist/management/__init__.py
playlist/management/commands/__init__.py
playlist/management/commands/update_playlists.py
playlist/templatetags/__init__.py
playlist/templatetags/playlist_template_tags.py